<annotation>
    <folder>../../Dataset/pubtabnet/train</folder>
    <filename>Multi‐Resonance Induced Thermally Activated_6__PMC3118875_038_00__PMC2604875_004_00.png</filename>
    <path>../SHARE/lg/imgs/Multi‐Resonance Induced Thermally Activated_6__PMC3118875_038_00__PMC2604875_004_00.png</path>
    <source>
        <database>Unknown</database>
    </source>
    <size>
        <width>595</width>
        <height>842</height>
        <depth>3</depth>
    </size>
    <segmented>0</segmented>
    <object>
        <name>cell</name>
        <pose>Unspecified</pose>
        <truncated>0</truncated>
        <difficult>0</difficult>
        <bndbox>
            <xmin>46</xmin>
            <ymin>79</ymin>
            <xmax>139</xmax>
            <ymax>93</ymax>
        </bndbox>
        <content_len>18</content_len>
    </object>
    <object>
        <name>cell</name>
        <pose>Unspecified</pose>
        <truncated>0</truncated>
        <difficult>0</difficult>
        <bndbox>
            <xmin>163</xmin>
            <ymin>71</ymin>
            <xmax>209</xmax>
            <ymax>100</ymax>
        </bndbox>
        <content_len>12</content_len>
    </object>
    <object>
        <name>cell</name>
        <pose>Unspecified</pose>
        <truncated>0</truncated>
        <difficult>0</difficult>
        <bndbox>
            <xmin>241</xmin>
            <ymin>71</ymin>
            <xmax>285</xmax>
            <ymax>100</ymax>
        </bndbox>
        <content_len>12</content_len>
    </object>
    <object>
        <name>cell</name>
        <pose>Unspecified</pose>
        <truncated>0</truncated>
        <difficult>0</difficult>
        <bndbox>
            <xmin>305</xmin>
            <ymin>71</ymin>
            <xmax>375</xmax>
            <ymax>100</ymax>
        </bndbox>
        <content_len>26</content_len>
    </object>
    <object>
        <name>cell</name>
        <pose>Unspecified</pose>
        <truncated>0</truncated>
        <difficult>0</difficult>
        <bndbox>
            <xmin>389</xmin>
            <ymin>79</ymin>
            <xmax>420</xmax>
            <ymax>93</ymax>
        </bndbox>
        <content_len>6</content_len>
    </object>
    <object>
        <name>cell</name>
        <pose>Unspecified</pose>
        <truncated>0</truncated>
        <difficult>0</difficult>
        <bndbox>
            <xmin>466</xmin>
            <ymin>71</ymin>
            <xmax>525</xmax>
            <ymax>100</ymax>
        </bndbox>
        <content_len>19</content_len>
    </object>
    <object>
        <name>cell</name>
        <pose>Unspecified</pose>
        <truncated>0</truncated>
        <difficult>0</difficult>
        <bndbox>
            <xmin>46</xmin>
            <ymin>110</ymin>
            <xmax>146</xmax>
            <ymax>123</ymax>
        </bndbox>
        <content_len>21</content_len>
    </object>
    <object>
        <name>cell</name>
        <pose>Unspecified</pose>
        <truncated>0</truncated>
        <difficult>0</difficult>
        <bndbox>
            <xmin>163</xmin>
            <ymin>110</ymin>
            <xmax>178</xmax>
            <ymax>123</ymax>
        </bndbox>
        <content_len>0</content_len>
    </object>
    <object>
        <name>cell</name>
        <pose>Unspecified</pose>
        <truncated>0</truncated>
        <difficult>0</difficult>
        <bndbox>
            <xmin>241</xmin>
            <ymin>110</ymin>
            <xmax>256</xmax>
            <ymax>123</ymax>
        </bndbox>
        <content_len>0</content_len>
    </object>
    <object>
        <name>cell</name>
        <pose>Unspecified</pose>
        <truncated>0</truncated>
        <difficult>0</difficult>
        <bndbox>
            <xmin>305</xmin>
            <ymin>102</ymin>
            <xmax>374</xmax>
            <ymax>131</ymax>
        </bndbox>
        <content_len>25</content_len>
    </object>
    <object>
        <name>cell</name>
        <pose>Unspecified</pose>
        <truncated>0</truncated>
        <difficult>0</difficult>
        <bndbox>
            <xmin>389</xmin>
            <ymin>110</ymin>
            <xmax>404</xmax>
            <ymax>123</ymax>
        </bndbox>
        <content_len>0</content_len>
    </object>
    <object>
        <name>cell</name>
        <pose>Unspecified</pose>
        <truncated>0</truncated>
        <difficult>0</difficult>
        <bndbox>
            <xmin>466</xmin>
            <ymin>110</ymin>
            <xmax>481</xmax>
            <ymax>123</ymax>
        </bndbox>
        <content_len>0</content_len>
    </object>
    <object>
        <name>cell</name>
        <pose>Unspecified</pose>
        <truncated>0</truncated>
        <difficult>0</difficult>
        <bndbox>
            <xmin>46</xmin>
            <ymin>133</ymin>
            <xmax>142</xmax>
            <ymax>161</ymax>
        </bndbox>
        <content_len>25</content_len>
    </object>
    <object>
        <name>cell</name>
        <pose>Unspecified</pose>
        <truncated>0</truncated>
        <difficult>0</difficult>
        <bndbox>
            <xmin>163</xmin>
            <ymin>133</ymin>
            <xmax>222</xmax>
            <ymax>162</ymax>
        </bndbox>
        <content_len>22</content_len>
    </object>
    <object>
        <name>cell</name>
        <pose>Unspecified</pose>
        <truncated>0</truncated>
        <difficult>0</difficult>
        <bndbox>
            <xmin>241</xmin>
            <ymin>140</ymin>
            <xmax>256</xmax>
            <ymax>154</ymax>
        </bndbox>
        <content_len>0</content_len>
    </object>
    <object>
        <name>cell</name>
        <pose>Unspecified</pose>
        <truncated>0</truncated>
        <difficult>0</difficult>
        <bndbox>
            <xmin>305</xmin>
            <ymin>140</ymin>
            <xmax>323</xmax>
            <ymax>154</ymax>
        </bndbox>
        <content_len>1</content_len>
    </object>
    <object>
        <name>cell</name>
        <pose>Unspecified</pose>
        <truncated>0</truncated>
        <difficult>0</difficult>
        <bndbox>
            <xmin>389</xmin>
            <ymin>140</ymin>
            <xmax>447</xmax>
            <ymax>154</ymax>
        </bndbox>
        <content_len>11</content_len>
    </object>
    <object>
        <name>cell</name>
        <pose>Unspecified</pose>
        <truncated>0</truncated>
        <difficult>0</difficult>
        <bndbox>
            <xmin>466</xmin>
            <ymin>140</ymin>
            <xmax>485</xmax>
            <ymax>154</ymax>
        </bndbox>
        <content_len>1</content_len>
    </object>
    <object>
        <name>cell</name>
        <pose>Unspecified</pose>
        <truncated>0</truncated>
        <difficult>0</difficult>
        <bndbox>
            <xmin>46</xmin>
            <ymin>163</ymin>
            <xmax>123</xmax>
            <ymax>192</ymax>
        </bndbox>
        <content_len>34</content_len>
    </object>
    <object>
        <name>cell</name>
        <pose>Unspecified</pose>
        <truncated>0</truncated>
        <difficult>0</difficult>
        <bndbox>
            <xmin>163</xmin>
            <ymin>171</ymin>
            <xmax>223</xmax>
            <ymax>184</ymax>
        </bndbox>
        <content_len>11</content_len>
    </object>
    <object>
        <name>cell</name>
        <pose>Unspecified</pose>
        <truncated>0</truncated>
        <difficult>0</difficult>
        <bndbox>
            <xmin>241</xmin>
            <ymin>171</ymin>
            <xmax>259</xmax>
            <ymax>184</ymax>
        </bndbox>
        <content_len>1</content_len>
    </object>
    <object>
        <name>cell</name>
        <pose>Unspecified</pose>
        <truncated>0</truncated>
        <difficult>0</difficult>
        <bndbox>
            <xmin>305</xmin>
            <ymin>171</ymin>
            <xmax>323</xmax>
            <ymax>184</ymax>
        </bndbox>
        <content_len>1</content_len>
    </object>
    <object>
        <name>cell</name>
        <pose>Unspecified</pose>
        <truncated>0</truncated>
        <difficult>0</difficult>
        <bndbox>
            <xmin>389</xmin>
            <ymin>171</ymin>
            <xmax>447</xmax>
            <ymax>184</ymax>
        </bndbox>
        <content_len>11</content_len>
    </object>
    <object>
        <name>cell</name>
        <pose>Unspecified</pose>
        <truncated>0</truncated>
        <difficult>0</difficult>
        <bndbox>
            <xmin>466</xmin>
            <ymin>171</ymin>
            <xmax>527</xmax>
            <ymax>184</ymax>
        </bndbox>
        <content_len>11</content_len>
    </object>
    <object>
        <name>cell</name>
        <pose>Unspecified</pose>
        <truncated>0</truncated>
        <difficult>0</difficult>
        <bndbox>
            <xmin>46</xmin>
            <ymin>194</ymin>
            <xmax>149</xmax>
            <ymax>207</ymax>
        </bndbox>
        <content_len>22</content_len>
    </object>
    <object>
        <name>cell</name>
        <pose>Unspecified</pose>
        <truncated>0</truncated>
        <difficult>0</difficult>
        <bndbox>
            <xmin>163</xmin>
            <ymin>194</ymin>
            <xmax>181</xmax>
            <ymax>207</ymax>
        </bndbox>
        <content_len>1</content_len>
    </object>
    <object>
        <name>cell</name>
        <pose>Unspecified</pose>
        <truncated>0</truncated>
        <difficult>0</difficult>
        <bndbox>
            <xmin>241</xmin>
            <ymin>194</ymin>
            <xmax>256</xmax>
            <ymax>207</ymax>
        </bndbox>
        <content_len>0</content_len>
    </object>
    <object>
        <name>cell</name>
        <pose>Unspecified</pose>
        <truncated>0</truncated>
        <difficult>0</difficult>
        <bndbox>
            <xmin>305</xmin>
            <ymin>194</ymin>
            <xmax>356</xmax>
            <ymax>207</ymax>
        </bndbox>
        <content_len>8</content_len>
    </object>
    <object>
        <name>cell</name>
        <pose>Unspecified</pose>
        <truncated>0</truncated>
        <difficult>0</difficult>
        <bndbox>
            <xmin>389</xmin>
            <ymin>194</ymin>
            <xmax>447</xmax>
            <ymax>207</ymax>
        </bndbox>
        <content_len>11</content_len>
    </object>
    <object>
        <name>cell</name>
        <pose>Unspecified</pose>
        <truncated>0</truncated>
        <difficult>0</difficult>
        <bndbox>
            <xmin>466</xmin>
            <ymin>194</ymin>
            <xmax>496</xmax>
            <ymax>207</ymax>
        </bndbox>
        <content_len>4</content_len>
    </object>
    <object>
        <name>cell</name>
        <pose>Unspecified</pose>
        <truncated>0</truncated>
        <difficult>0</difficult>
        <bndbox>
            <xmin>46</xmin>
            <ymin>209</ymin>
            <xmax>91</xmax>
            <ymax>223</ymax>
        </bndbox>
        <content_len>6</content_len>
    </object>
    <object>
        <name>cell</name>
        <pose>Unspecified</pose>
        <truncated>0</truncated>
        <difficult>0</difficult>
        <bndbox>
            <xmin>163</xmin>
            <ymin>209</ymin>
            <xmax>214</xmax>
            <ymax>223</ymax>
        </bndbox>
        <content_len>8</content_len>
    </object>
    <object>
        <name>cell</name>
        <pose>Unspecified</pose>
        <truncated>0</truncated>
        <difficult>0</difficult>
        <bndbox>
            <xmin>241</xmin>
            <ymin>209</ymin>
            <xmax>259</xmax>
            <ymax>223</ymax>
        </bndbox>
        <content_len>1</content_len>
    </object>
    <object>
        <name>cell</name>
        <pose>Unspecified</pose>
        <truncated>0</truncated>
        <difficult>0</difficult>
        <bndbox>
            <xmin>305</xmin>
            <ymin>209</ymin>
            <xmax>323</xmax>
            <ymax>223</ymax>
        </bndbox>
        <content_len>1</content_len>
    </object>
    <object>
        <name>cell</name>
        <pose>Unspecified</pose>
        <truncated>0</truncated>
        <difficult>0</difficult>
        <bndbox>
            <xmin>389</xmin>
            <ymin>209</ymin>
            <xmax>447</xmax>
            <ymax>223</ymax>
        </bndbox>
        <content_len>11</content_len>
    </object>
    <object>
        <name>cell</name>
        <pose>Unspecified</pose>
        <truncated>0</truncated>
        <difficult>0</difficult>
        <bndbox>
            <xmin>466</xmin>
            <ymin>209</ymin>
            <xmax>485</xmax>
            <ymax>223</ymax>
        </bndbox>
        <content_len>1</content_len>
    </object>
    <object>
        <name>cell</name>
        <pose>Unspecified</pose>
        <truncated>0</truncated>
        <difficult>0</difficult>
        <bndbox>
            <xmin>46</xmin>
            <ymin>225</ymin>
            <xmax>130</xmax>
            <ymax>253</ymax>
        </bndbox>
        <content_len>32</content_len>
    </object>
    <object>
        <name>cell</name>
        <pose>Unspecified</pose>
        <truncated>0</truncated>
        <difficult>0</difficult>
        <bndbox>
            <xmin>163</xmin>
            <ymin>225</ymin>
            <xmax>214</xmax>
            <ymax>253</ymax>
        </bndbox>
        <content_len>13</content_len>
    </object>
    <object>
        <name>cell</name>
        <pose>Unspecified</pose>
        <truncated>0</truncated>
        <difficult>0</difficult>
        <bndbox>
            <xmin>241</xmin>
            <ymin>225</ymin>
            <xmax>292</xmax>
            <ymax>253</ymax>
        </bndbox>
        <content_len>13</content_len>
    </object>
    <object>
        <name>cell</name>
        <pose>Unspecified</pose>
        <truncated>0</truncated>
        <difficult>0</difficult>
        <bndbox>
            <xmin>305</xmin>
            <ymin>225</ymin>
            <xmax>356</xmax>
            <ymax>253</ymax>
        </bndbox>
        <content_len>13</content_len>
    </object>
    <object>
        <name>cell</name>
        <pose>Unspecified</pose>
        <truncated>0</truncated>
        <difficult>0</difficult>
        <bndbox>
            <xmin>389</xmin>
            <ymin>225</ymin>
            <xmax>454</xmax>
            <ymax>253</ymax>
        </bndbox>
        <content_len>22</content_len>
    </object>
    <object>
        <name>cell</name>
        <pose>Unspecified</pose>
        <truncated>0</truncated>
        <difficult>0</difficult>
        <bndbox>
            <xmin>466</xmin>
            <ymin>225</ymin>
            <xmax>518</xmax>
            <ymax>253</ymax>
        </bndbox>
        <content_len>13</content_len>
    </object>
    <object>
        <name>cell</name>
        <pose>Unspecified</pose>
        <truncated>0</truncated>
        <difficult>0</difficult>
        <bndbox>
            <xmin>46</xmin>
            <ymin>255</ymin>
            <xmax>135</xmax>
            <ymax>284</ymax>
        </bndbox>
        <content_len>41</content_len>
    </object>
    <object>
        <name>cell</name>
        <pose>Unspecified</pose>
        <truncated>0</truncated>
        <difficult>0</difficult>
        <bndbox>
            <xmin>163</xmin>
            <ymin>263</ymin>
            <xmax>178</xmax>
            <ymax>276</ymax>
        </bndbox>
        <content_len>0</content_len>
    </object>
    <object>
        <name>cell</name>
        <pose>Unspecified</pose>
        <truncated>0</truncated>
        <difficult>0</difficult>
        <bndbox>
            <xmin>241</xmin>
            <ymin>263</ymin>
            <xmax>256</xmax>
            <ymax>276</ymax>
        </bndbox>
        <content_len>0</content_len>
    </object>
    <object>
        <name>cell</name>
        <pose>Unspecified</pose>
        <truncated>0</truncated>
        <difficult>0</difficult>
        <bndbox>
            <xmin>305</xmin>
            <ymin>263</ymin>
            <xmax>319</xmax>
            <ymax>276</ymax>
        </bndbox>
        <content_len>0</content_len>
    </object>
    <object>
        <name>cell</name>
        <pose>Unspecified</pose>
        <truncated>0</truncated>
        <difficult>0</difficult>
        <bndbox>
            <xmin>389</xmin>
            <ymin>263</ymin>
            <xmax>443</xmax>
            <ymax>276</ymax>
        </bndbox>
        <content_len>10</content_len>
    </object>
    <object>
        <name>cell</name>
        <pose>Unspecified</pose>
        <truncated>0</truncated>
        <difficult>0</difficult>
        <bndbox>
            <xmin>466</xmin>
            <ymin>263</ymin>
            <xmax>481</xmax>
            <ymax>276</ymax>
        </bndbox>
        <content_len>0</content_len>
    </object>
    <object>
        <name>cell</name>
        <pose>Unspecified</pose>
        <truncated>0</truncated>
        <difficult>0</difficult>
        <bndbox>
            <xmin>46</xmin>
            <ymin>286</ymin>
            <xmax>116</xmax>
            <ymax>314</ymax>
        </bndbox>
        <content_len>30</content_len>
    </object>
    <object>
        <name>cell</name>
        <pose>Unspecified</pose>
        <truncated>0</truncated>
        <difficult>0</difficult>
        <bndbox>
            <xmin>163</xmin>
            <ymin>293</ymin>
            <xmax>223</xmax>
            <ymax>307</ymax>
        </bndbox>
        <content_len>11</content_len>
    </object>
    <object>
        <name>cell</name>
        <pose>Unspecified</pose>
        <truncated>0</truncated>
        <difficult>0</difficult>
        <bndbox>
            <xmin>241</xmin>
            <ymin>293</ymin>
            <xmax>259</xmax>
            <ymax>307</ymax>
        </bndbox>
        <content_len>1</content_len>
    </object>
    <object>
        <name>cell</name>
        <pose>Unspecified</pose>
        <truncated>0</truncated>
        <difficult>0</difficult>
        <bndbox>
            <xmin>305</xmin>
            <ymin>293</ymin>
            <xmax>365</xmax>
            <ymax>307</ymax>
        </bndbox>
        <content_len>11</content_len>
    </object>
    <object>
        <name>cell</name>
        <pose>Unspecified</pose>
        <truncated>0</truncated>
        <difficult>0</difficult>
        <bndbox>
            <xmin>389</xmin>
            <ymin>293</ymin>
            <xmax>451</xmax>
            <ymax>307</ymax>
        </bndbox>
        <content_len>12</content_len>
    </object>
    <object>
        <name>cell</name>
        <pose>Unspecified</pose>
        <truncated>0</truncated>
        <difficult>0</difficult>
        <bndbox>
            <xmin>466</xmin>
            <ymin>293</ymin>
            <xmax>527</xmax>
            <ymax>307</ymax>
        </bndbox>
        <content_len>11</content_len>
    </object>
    <object>
        <name>cell</name>
        <pose>Unspecified</pose>
        <truncated>0</truncated>
        <difficult>0</difficult>
        <bndbox>
            <xmin>46</xmin>
            <ymin>324</ymin>
            <xmax>119</xmax>
            <ymax>367</ymax>
        </bndbox>
        <content_len>39</content_len>
    </object>
    <object>
        <name>cell</name>
        <pose>Unspecified</pose>
        <truncated>0</truncated>
        <difficult>0</difficult>
        <bndbox>
            <xmin>163</xmin>
            <ymin>322</ymin>
            <xmax>223</xmax>
            <ymax>367</ymax>
        </bndbox>
        <content_len>33</content_len>
    </object>
    <object>
        <name>cell</name>
        <pose>Unspecified</pose>
        <truncated>0</truncated>
        <difficult>0</difficult>
        <bndbox>
            <xmin>241</xmin>
            <ymin>316</ymin>
            <xmax>294</xmax>
            <ymax>375</ymax>
        </bndbox>
        <content_len>40</content_len>
    </object>
    <object>
        <name>cell</name>
        <pose>Unspecified</pose>
        <truncated>0</truncated>
        <difficult>0</difficult>
        <bndbox>
            <xmin>305</xmin>
            <ymin>322</ymin>
            <xmax>385</xmax>
            <ymax>368</ymax>
        </bndbox>
        <content_len>42</content_len>
    </object>
    <object>
        <name>cell</name>
        <pose>Unspecified</pose>
        <truncated>0</truncated>
        <difficult>0</difficult>
        <bndbox>
            <xmin>389</xmin>
            <ymin>316</ymin>
            <xmax>456</xmax>
            <ymax>375</ymax>
        </bndbox>
        <content_len>47</content_len>
    </object>
    <object>
        <name>cell</name>
        <pose>Unspecified</pose>
        <truncated>0</truncated>
        <difficult>0</difficult>
        <bndbox>
            <xmin>466</xmin>
            <ymin>322</ymin>
            <xmax>545</xmax>
            <ymax>367</ymax>
        </bndbox>
        <content_len>38</content_len>
    </object>
    <object>
        <name>borderless</name>
        <pose>Unspecified</pose>
        <truncated>0</truncated>
        <difficult>0</difficult>
        <bndbox>
            <xmin>46</xmin>
            <ymin>68</ymin>
            <xmax>547</xmax>
            <ymax>375</ymax>
        </bndbox>
    </object>
    <object>
        <name>cell</name>
        <pose>Unspecified</pose>
        <truncated>0</truncated>
        <difficult>0</difficult>
        <bndbox>
            <xmin>50</xmin>
            <ymin>398</ymin>
            <xmax>88</xmax>
            <ymax>407</ymax>
        </bndbox>
        <content_len>8</content_len>
    </object>
    <object>
        <name>cell</name>
        <pose>Unspecified</pose>
        <truncated>0</truncated>
        <difficult>0</difficult>
        <bndbox>
            <xmin>217</xmin>
            <ymin>398</ymin>
            <xmax>240</xmax>
            <ymax>407</ymax>
        </bndbox>
        <content_len>5</content_len>
    </object>
    <object>
        <name>cell</name>
        <pose>Unspecified</pose>
        <truncated>0</truncated>
        <difficult>0</difficult>
        <bndbox>
            <xmin>383</xmin>
            <ymin>398</ymin>
            <xmax>410</xmax>
            <ymax>407</ymax>
        </bndbox>
        <content_len>6</content_len>
    </object>
    <object>
        <name>cell</name>
        <pose>Unspecified</pose>
        <truncated>0</truncated>
        <difficult>0</difficult>
        <bndbox>
            <xmin>50</xmin>
            <ymin>420</ymin>
            <xmax>134</xmax>
            <ymax>429</ymax>
        </bndbox>
        <content_len>22</content_len>
    </object>
    <object>
        <name>cell</name>
        <pose>Unspecified</pose>
        <truncated>0</truncated>
        <difficult>0</difficult>
        <bndbox>
            <xmin>217</xmin>
            <ymin>420</ymin>
            <xmax>367</xmax>
            <ymax>439</ymax>
        </bndbox>
        <content_len>46</content_len>
    </object>
    <object>
        <name>cell</name>
        <pose>Unspecified</pose>
        <truncated>0</truncated>
        <difficult>0</difficult>
        <bndbox>
            <xmin>50</xmin>
            <ymin>451</ymin>
            <xmax>145</xmax>
            <ymax>461</ymax>
        </bndbox>
        <content_len>26</content_len>
    </object>
    <object>
        <name>cell</name>
        <pose>Unspecified</pose>
        <truncated>0</truncated>
        <difficult>0</difficult>
        <bndbox>
            <xmin>217</xmin>
            <ymin>451</ymin>
            <xmax>299</xmax>
            <ymax>461</ymax>
        </bndbox>
        <content_len>20</content_len>
    </object>
    <object>
        <name>cell</name>
        <pose>Unspecified</pose>
        <truncated>0</truncated>
        <difficult>0</difficult>
        <bndbox>
            <xmin>50</xmin>
            <ymin>473</ymin>
            <xmax>193</xmax>
            <ymax>492</ymax>
        </bndbox>
        <content_len>58</content_len>
    </object>
    <object>
        <name>cell</name>
        <pose>Unspecified</pose>
        <truncated>0</truncated>
        <difficult>0</difficult>
        <bndbox>
            <xmin>383</xmin>
            <ymin>473</ymin>
            <xmax>481</xmax>
            <ymax>483</ymax>
        </bndbox>
        <content_len>24</content_len>
    </object>
    <object>
        <name>cell</name>
        <pose>Unspecified</pose>
        <truncated>0</truncated>
        <difficult>0</difficult>
        <bndbox>
            <xmin>50</xmin>
            <ymin>505</ymin>
            <xmax>205</xmax>
            <ymax>524</ymax>
        </bndbox>
        <content_len>50</content_len>
    </object>
    <object>
        <name>cell</name>
        <pose>Unspecified</pose>
        <truncated>0</truncated>
        <difficult>0</difficult>
        <bndbox>
            <xmin>383</xmin>
            <ymin>505</ymin>
            <xmax>442</xmax>
            <ymax>515</ymax>
        </bndbox>
        <content_len>13</content_len>
    </object>
    <object>
        <name>cell</name>
        <pose>Unspecified</pose>
        <truncated>0</truncated>
        <difficult>0</difficult>
        <bndbox>
            <xmin>50</xmin>
            <ymin>536</ymin>
            <xmax>190</xmax>
            <ymax>546</ymax>
        </bndbox>
        <content_len>39</content_len>
    </object>
    <object>
        <name>cell</name>
        <pose>Unspecified</pose>
        <truncated>0</truncated>
        <difficult>0</difficult>
        <bndbox>
            <xmin>383</xmin>
            <ymin>536</ymin>
            <xmax>538</xmax>
            <ymax>555</ymax>
        </bndbox>
        <content_len>54</content_len>
    </object>
    <object>
        <name>cell</name>
        <pose>Unspecified</pose>
        <truncated>0</truncated>
        <difficult>0</difficult>
        <bndbox>
            <xmin>50</xmin>
            <ymin>568</ymin>
            <xmax>131</xmax>
            <ymax>578</ymax>
        </bndbox>
        <content_len>21</content_len>
    </object>
    <object>
        <name>cell</name>
        <pose>Unspecified</pose>
        <truncated>0</truncated>
        <difficult>0</difficult>
        <bndbox>
            <xmin>383</xmin>
            <ymin>568</ymin>
            <xmax>532</xmax>
            <ymax>587</ymax>
        </bndbox>
        <content_len>51</content_len>
    </object>
    <object>
        <name>cell</name>
        <pose>Unspecified</pose>
        <truncated>0</truncated>
        <difficult>0</difficult>
        <bndbox>
            <xmin>50</xmin>
            <ymin>599</ymin>
            <xmax>156</xmax>
            <ymax>609</ymax>
        </bndbox>
        <content_len>29</content_len>
    </object>
    <object>
        <name>cell</name>
        <pose>Unspecified</pose>
        <truncated>0</truncated>
        <difficult>0</difficult>
        <bndbox>
            <xmin>383</xmin>
            <ymin>599</ymin>
            <xmax>474</xmax>
            <ymax>609</ymax>
        </bndbox>
        <content_len>23</content_len>
    </object>
    <object>
        <name>cell</name>
        <pose>Unspecified</pose>
        <truncated>0</truncated>
        <difficult>0</difficult>
        <bndbox>
            <xmin>50</xmin>
            <ymin>622</ymin>
            <xmax>113</xmax>
            <ymax>631</ymax>
        </bndbox>
        <content_len>15</content_len>
    </object>
    <object>
        <name>cell</name>
        <pose>Unspecified</pose>
        <truncated>0</truncated>
        <difficult>0</difficult>
        <bndbox>
            <xmin>383</xmin>
            <ymin>622</ymin>
            <xmax>418</xmax>
            <ymax>631</ymax>
        </bndbox>
        <content_len>5</content_len>
    </object>
    <object>
        <name>cell</name>
        <pose>Unspecified</pose>
        <truncated>0</truncated>
        <difficult>0</difficult>
        <bndbox>
            <xmin>50</xmin>
            <ymin>644</ymin>
            <xmax>200</xmax>
            <ymax>663</ymax>
        </bndbox>
        <content_len>59</content_len>
    </object>
    <object>
        <name>cell</name>
        <pose>Unspecified</pose>
        <truncated>0</truncated>
        <difficult>0</difficult>
        <bndbox>
            <xmin>217</xmin>
            <ymin>644</ymin>
            <xmax>251</xmax>
            <ymax>654</ymax>
        </bndbox>
        <content_len>5</content_len>
    </object>
    <object>
        <name>cell</name>
        <pose>Unspecified</pose>
        <truncated>0</truncated>
        <difficult>0</difficult>
        <bndbox>
            <xmin>383</xmin>
            <ymin>644</ymin>
            <xmax>418</xmax>
            <ymax>654</ymax>
        </bndbox>
        <content_len>5</content_len>
    </object>
    <object>
        <name>cell</name>
        <pose>Unspecified</pose>
        <truncated>0</truncated>
        <difficult>0</difficult>
        <bndbox>
            <xmin>50</xmin>
            <ymin>675</ymin>
            <xmax>175</xmax>
            <ymax>694</ymax>
        </bndbox>
        <content_len>56</content_len>
    </object>
    <object>
        <name>cell</name>
        <pose>Unspecified</pose>
        <truncated>0</truncated>
        <difficult>0</difficult>
        <bndbox>
            <xmin>217</xmin>
            <ymin>675</ymin>
            <xmax>236</xmax>
            <ymax>685</ymax>
        </bndbox>
        <content_len>3</content_len>
    </object>
    <object>
        <name>cell</name>
        <pose>Unspecified</pose>
        <truncated>0</truncated>
        <difficult>0</difficult>
        <bndbox>
            <xmin>50</xmin>
            <ymin>707</ymin>
            <xmax>185</xmax>
            <ymax>717</ymax>
        </bndbox>
        <content_len>37</content_len>
    </object>
    <object>
        <name>cell</name>
        <pose>Unspecified</pose>
        <truncated>0</truncated>
        <difficult>0</difficult>
        <bndbox>
            <xmin>383</xmin>
            <ymin>707</ymin>
            <xmax>536</xmax>
            <ymax>726</ymax>
        </bndbox>
        <content_len>52</content_len>
    </object>
    <object>
        <name>borderless</name>
        <pose>Unspecified</pose>
        <truncated>0</truncated>
        <difficult>0</difficult>
        <bndbox>
            <xmin>47</xmin>
            <ymin>393</ymin>
            <xmax>547</xmax>
            <ymax>732</ymax>
        </bndbox>
    </object>
</annotation>
